device_analysis/__init__.py
device_analysis/cpu_metrics.py
device_analysis/memory_metrics.py
device_analysis/network_metrics.py
device_analysis/os_specific/__init__.py
device_analysis/os_specific/linux_metrics.py
device_analysis/os_specific/macos_metrics.py
device_analysis/os_specific/windows_metrics.py
device_analysis-0.1.0.dist-info/METADATA
device_analysis-0.1.0.dist-info/WHEEL
device_analysis-0.1.0.dist-info/entry_points.txt
device_analysis-0.1.0.dist-info/top_level.txt
device_analysis-0.1.0.dist-info/RECORD
